[
    {
        "artist": "ANTLRS",
        "album": "Invest",
        "release_date": "2025-12-22",
        "genre": "Metalcore, Progressive Metal, Metal",
        "url": "https://www.albumoftheyear.org/album/1588924-antlrs-invest.php"
    },
    {
        "artist": "Amulet",
        "album": "Don't Say The Anguish Took Her Life",
        "release_date": "2025-12-20",
        "genre": "Metalcore, Metal",
        "url": "https://www.albumoftheyear.org/album/1583946-amulet-dont-say-the-anguish-took-her-life.php"
    },
    {
        "artist": "Lychgate",
        "album": "Precipice",
        "release_date": "2025-12-19",
        "genre": "Metal",
        "url": "https://www.albumoftheyear.org/album/1542720-lychgate-precipice.php"
    },
    {
        "artist": "LVCAS",
        "album": "abatido mas não derrotado",
        "release_date": "2025-12-16",
        "genre": "Metal",
        "url": "https://www.albumoftheyear.org/album/1542365-lvcas-abatido-mas-nao-derrotado.php"
    },
    {
        "artist": "Jordan Liubenov",
        "album": "TODE",
        "release_date": "2025-12-13",
        "genre": "Metalcore, Progressive Metal, Metal",
        "url": "https://www.albumoftheyear.org/album/1577613-jordan-liubenov-tode.php"
    },
    {
        "artist": "Rotten Sound",
        "album": "Mass Extinction",
        "release_date": "2025-12-12",
        "genre": "Death Metal, Metal",
        "url": "https://www.albumoftheyear.org/album/1519226-rotten-sound-mass-extinction.php"
    },
    {
        "artist": "Fleshvessel",
        "album": "Obstinacy: Sisyphean Dreams Unfolded",
        "release_date": "2025-12-12",
        "genre": "Death Metal, Progressive Metal, Metal",
        "url": "https://www.albumoftheyear.org/album/1530974-fleshvessel-obstinacy-sisyphean-dreams-unfolded.php"
    },
    {
        "artist": "Olympus Lenticular",
        "album": "Summit of Agony",
        "release_date": "2025-12-12",
        "genre": "Metalcore, Progressive Metal, Metal",
        "url": "https://www.albumoftheyear.org/album/1574333-olympus-lenticular-summit-of-agony.php"
    },
    {
        "artist": "Pincer+",
        "album": "Who Are You When No One’s Around",
        "release_date": "2025-12-12",
        "genre": "Metalcore, Metal",
        "url": "https://www.albumoftheyear.org/album/1573420-pincer-who-are-you-when-no-ones-around.php"
    },
    {
        "artist": "Abbie Falls",
        "album": "Life Is Just A Temporary Plan",
        "release_date": "2025-12-12",
        "genre": "Metalcore, Metal",
        "url": "https://www.albumoftheyear.org/album/1434971-abbie-falls-life-is-just-a-temporary-plan.php"
    },
    {
        "artist": "Enezothe",
        "album": "An Audience with God",
        "release_date": "2025-12-12",
        "genre": "Metalcore",
        "url": "https://www.albumoftheyear.org/album/1540598-enezothe-an-audience-with-god.php"
    },
    {
        "artist": "Volumes",
        "album": "Mirror Touch",
        "release_date": "2025-12-12",
        "genre": "Progressive Metal, Metal",
        "url": "https://www.albumoftheyear.org/album/1521177-volumes-mirror-touch.php"
    },
    {
        "artist": "KILL KARL",
        "album": "SUCK ON MY ALBUM",
        "release_date": "2025-12-12",
        "genre": "Metal",
        "url": "https://www.albumoftheyear.org/album/1566426-kill-karl-suck-on-my-album.php"
    },
    {
        "artist": "Codefendants",
        "album": "Live From Red Lion Recording Studio",
        "release_date": "2025-12-12",
        "genre": "Metal",
        "url": "https://www.albumoftheyear.org/album/1581048-codefendants-live-from-red-lion-recording-studio.php"
    },
    {
        "artist": "Codetalker",
        "album": "PNEUMA: SIDE B",
        "release_date": "2025-12-11",
        "genre": "Metalcore",
        "url": "https://www.albumoftheyear.org/album/1573254-codetalker-pneuma-side-b.php"
    },
    {
        "artist": "HEALTH",
        "album": "CONFLICT DLC",
        "release_date": "2025-12-11",
        "genre": "Metal",
        "url": "https://www.albumoftheyear.org/album/1462951-health-conflict-dlc.php"
    },
    {
        "artist": "Sybreed",
        "album": "Bonus Tracks",
        "release_date": "2025-12-11",
        "genre": "Metal",
        "url": "https://www.albumoftheyear.org/album/1548788-sybreed-bonus-tracks.php"
    },
    {
        "artist": "Chasse-Neige",
        "album": "Joual Black Metal",
        "release_date": "2025-12-09",
        "genre": "Black Metal, Metal",
        "url": "https://www.albumoftheyear.org/album/1578719-chasse-neige-joual-black-metal.php"
    },
    {
        "artist": "Converge",
        "album": "Converge | Audiotree From Nothing",
        "release_date": "2025-12-08",
        "genre": "Metalcore, Metal",
        "url": "https://www.albumoftheyear.org/album/1570078-converge-converge-audiotree-from-nothing.php"
    },
    {
        "artist": "Doki-Doki",
        "album": "Broken Birds",
        "release_date": "2025-12-06",
        "genre": "Progressive Metal, Metal",
        "url": "https://www.albumoftheyear.org/album/1570955-doki-doki-broken-birds.php"
    },
    {
        "artist": "Blood Red Throne",
        "album": "Siltskin",
        "release_date": "2025-12-05",
        "genre": "Death Metal, Metal",
        "url": "https://www.albumoftheyear.org/album/1480631-blood-red-throne-siltskin.php"
    },
    {
        "artist": "Enthroned",
        "album": "Ashspawn",
        "release_date": "2025-12-05",
        "genre": "Death Metal, Metal",
        "url": "https://www.albumoftheyear.org/album/1477525-enthroned-ashspawn.php"
    },
    {
        "artist": "Sulfuric Cautery",
        "album": "CONSUMMATE EXTIRPATION",
        "release_date": "2025-12-05",
        "genre": "Death Metal, Metal",
        "url": "https://www.albumoftheyear.org/album/1562201-sulfuric-cautery-consummate-extirpation.php"
    },
    {
        "artist": "Upon a Burning Body",
        "album": "Blood of The Bull",
        "release_date": "2025-12-05",
        "genre": "Groove Metal, Metal",
        "url": "https://www.albumoftheyear.org/album/1537181-upon-a-burning-body-blood-of-the-bull.php"
    },
    {
        "artist": "Despite Exile",
        "album": "Where Hope Goes To Die",
        "release_date": "2025-12-05",
        "genre": "Metalcore, Metal",
        "url": "https://www.albumoftheyear.org/album/1517540-despite-exile-where-hope-goes-to-die.php"
    },
    {
        "artist": "Witness Chamber",
        "album": "Bronze Gates",
        "release_date": "2025-12-05",
        "genre": "Metalcore, Metal",
        "url": "https://www.albumoftheyear.org/album/1566062-witness-chamber-bronze-gates.php"
    },
    {
        "artist": "Kakihara",
        "album": "Love Songs, Pt. 2",
        "release_date": "2025-12-05",
        "genre": "Metalcore, Metal",
        "url": "https://www.albumoftheyear.org/album/1566466-kakihara-love-songs-pt-2.php"
    },
    {
        "artist": "Chained Saint",
        "album": "Live at the Whiskey a Go Go - EP",
        "release_date": "2025-12-05",
        "genre": "Thrash Metal, Metal",
        "url": "https://www.albumoftheyear.org/album/1566560-chained-saint-live-at-the-whiskey-a-go-go-ep.php"
    },
    {
        "artist": "Set For Tomorrow",
        "album": "ARCS",
        "release_date": "2025-12-05",
        "genre": "Metal",
        "url": "https://www.albumoftheyear.org/album/1506882-set-for-tomorrow-arcs.php"
    },
    {
        "artist": "Guttural Slug",
        "album": "Ulcers In The Flesh Of Thought",
        "release_date": "2025-12-05",
        "genre": "Metal",
        "url": "https://www.albumoftheyear.org/album/1565660-guttural-slug-ulcers-in-the-flesh-of-thought.php"
    },
    {
        "artist": "Trhä",
        "album": "tahaccet ga qëcha com ibajn",
        "release_date": "2025-12-04",
        "genre": "Black Metal, Metal",
        "url": "https://www.albumoftheyear.org/album/1564634-trha-tahaccet-ga-qecha-com-ibajn.php"
    },
    {
        "artist": "Barbelith",
        "album": "BARBELITH / TRHÄ",
        "release_date": "2025-12-04",
        "genre": "Black Metal, Metal",
        "url": "https://www.albumoftheyear.org/album/1555850-barbelith-barbelith-trha.php"
    },
    {
        "artist": "Zero State",
        "album": "Shadow Realm",
        "release_date": "2025-12-04",
        "genre": "Death Metal, Metal",
        "url": "https://www.albumoftheyear.org/album/1564780-zero-state-shadow-realm.php"
    },
    {
        "artist": "Profiler",
        "album": "Masquerading Self",
        "release_date": "2025-12-04",
        "genre": "Metal",
        "url": "https://www.albumoftheyear.org/album/1480758-profiler-masquerading-self.php"
    },
    {
        "artist": "The Flob",
        "album": "TỐI THƯỢNG",
        "release_date": "2025-12-04",
        "genre": "Metal",
        "url": "https://www.albumoftheyear.org/album/1543799-the-flob-toi-thuong.php"
    },
    {
        "artist": "Celldweller",
        "album": "An Offworld Christmas",
        "release_date": "2025-12-03",
        "genre": "Metal",
        "url": "https://www.albumoftheyear.org/album/1546415-celldweller-an-offworld-christmas.php"
    },
    {
        "artist": "Jutes",
        "album": "Dilworth",
        "release_date": "2025-12-03",
        "genre": "Metal",
        "url": "https://www.albumoftheyear.org/album/1331162-jutes-dilworth.php"
    },
    {
        "artist": "Execution",
        "album": "Its About Murder",
        "release_date": "2025-12-02",
        "genre": "Metalcore, Metal",
        "url": "https://www.albumoftheyear.org/album/1566467-execution-its-about-murder.php"
    },
    {
        "artist": "Shining",
        "album": "Feberdrömmar (Del Två)",
        "release_date": "2025-12-01",
        "genre": "Black Metal, Metal",
        "url": "https://www.albumoftheyear.org/album/1534387-shining-feberdrommar-del-tva.php"
    },
    {
        "artist": "Black Winged",
        "album": "Frost",
        "release_date": "2025-12-01",
        "genre": "Metalcore, Progressive Metal, Metal",
        "url": "https://www.albumoftheyear.org/album/1570286-black-winged-frost.php"
    },
    {
        "artist": "Ends In Tragedy",
        "album": "Beauty Of Death",
        "release_date": "2025-11-30",
        "genre": "Metalcore, Metal",
        "url": "https://www.albumoftheyear.org/album/1558566-ends-in-tragedy-beauty-of-death.php"
    },
    {
        "artist": "XavlegbmaofffassssitimiwoamndutroabcwapwaeiippohfffX",
        "album": "Hippopotomonstrosesquippedaliophobia",
        "release_date": "2025-11-30",
        "genre": "Metalcore, Metal",
        "url": "https://www.albumoftheyear.org/album/1532139-xavlegbmaofffassssitimiwoamndutroabcwapwaeiippohfffx-hippopotomonstrosesquippedaliophobia.php"
    },
    {
        "artist": "Carmen Sixteen",
        "album": "...And Grins With Sharpened Teeth...",
        "release_date": "2025-11-29",
        "genre": "Metalcore",
        "url": "https://www.albumoftheyear.org/album/1557872-carmen-sixteen-and-grins-with-sharpened-teeth.php"
    },
    {
        "artist": "Blut aus Nord",
        "album": "Ethereal Horizons",
        "release_date": "2025-11-28",
        "genre": "Black Metal, Metal",
        "url": "https://www.albumoftheyear.org/album/1447080-blut-aus-nord-ethereal-horizons.php"
    },
    {
        "artist": "1349",
        "album": "Winter Mass",
        "release_date": "2025-11-28",
        "genre": "Black Metal, Metal",
        "url": "https://www.albumoftheyear.org/album/1563814-1349-winter-mass.php"
    },
    {
        "artist": "Nordicwinter",
        "album": "Solitude",
        "release_date": "2025-11-28",
        "genre": "Black Metal, Metal",
        "url": "https://www.albumoftheyear.org/album/1525376-nordicwinter-solitude.php"
    },
    {
        "artist": "Lungtoucher",
        "album": "My Consort, Eternal",
        "release_date": "2025-11-28",
        "genre": "Black Metal, Metal",
        "url": "https://www.albumoftheyear.org/album/1557043-lungtoucher-my-consort-eternal.php"
    },
    {
        "artist": "Dead And Dripping",
        "album": "Nefarious Scintillations",
        "release_date": "2025-11-28",
        "genre": "Death Metal, Metal",
        "url": "https://www.albumoftheyear.org/album/1507198-dead-and-dripping-nefarious-scintillations.php"
    },
    {
        "artist": "Godeater",
        "album": "Alvorecer",
        "release_date": "2025-11-28",
        "genre": "Death Metal, Metalcore, Metal",
        "url": "https://www.albumoftheyear.org/album/1544924-godeater-alvorecer.php"
    },
    {
        "artist": "Phobocosm",
        "album": "Gateway",
        "release_date": "2025-11-28",
        "genre": "Doom Metal, Metal",
        "url": "https://www.albumoftheyear.org/album/1525377-phobocosm-gateway.php"
    },
    {
        "artist": "Excide",
        "album": "Bastard Hymns",
        "release_date": "2025-11-28",
        "genre": "Metalcore, Metal",
        "url": "https://www.albumoftheyear.org/album/1455442-excide-bastard-hymns.php"
    },
    {
        "artist": "Fallweather",
        "album": "You For Life",
        "release_date": "2025-11-28",
        "genre": "Metalcore, Metal",
        "url": "https://www.albumoftheyear.org/album/1556290-fallweather-you-for-life.php"
    },
    {
        "artist": "xVERITEx",
        "album": "For a Scorn-Forged Hear",
        "release_date": "2025-11-28",
        "genre": "Metalcore, Metal",
        "url": "https://www.albumoftheyear.org/album/1558629-xveritex-for-a-scorn-forged-hear.php"
    },
    {
        "artist": "TILLDEATHDOUSPART",
        "album": "THE BURDEN OF ETERNITY",
        "release_date": "2025-11-28",
        "genre": "Metalcore, Metal",
        "url": "https://www.albumoftheyear.org/album/1557849-tilldeathdouspart-the-burden-of-eternity.php"
    },
    {
        "artist": "Wings of Existence",
        "album": "Her House",
        "release_date": "2025-11-28",
        "genre": "Metalcore, Metal",
        "url": "https://www.albumoftheyear.org/album/1560817-wings-of-existence-her-house.php"
    },
    {
        "artist": "Struck A Nerve",
        "album": "Struck A Nerve",
        "release_date": "2025-11-28",
        "genre": "Thrash Metal, Metal",
        "url": "https://www.albumoftheyear.org/album/1485105-struck-a-nerve-struck-a-nerve.php"
    },
    {
        "artist": "Equilibrium",
        "album": "Equinox",
        "release_date": "2025-11-28",
        "genre": "Metal",
        "url": "https://www.albumoftheyear.org/album/1486096-equilibrium-equinox.php"
    },
    {
        "artist": "Forced Deglovement",
        "album": "Demo EP",
        "release_date": "2025-11-28",
        "genre": "Metal",
        "url": "https://www.albumoftheyear.org/album/1556250-forced-deglovement-demo-ep.php"
    },
    {
        "artist": "DEVILHUSK",
        "album": "SLEEP LIKE THE DEAD",
        "release_date": "2025-11-27",
        "genre": "Metalcore",
        "url": "https://www.albumoftheyear.org/album/1560821-devilhusk-sleep-like-the-dead.php"
    },
    {
        "artist": "Feather Mountain",
        "album": "A Liminal Step",
        "release_date": "2025-11-27",
        "genre": "Progressive Metal, Metal",
        "url": "https://www.albumoftheyear.org/album/1472157-feather-mountain-a-liminal-step.php"
    },
    {
        "artist": "Puritan Bone",
        "album": "Ecstasy on the Frontier of Blood",
        "release_date": "2025-11-26",
        "genre": "Black Metal",
        "url": "https://www.albumoftheyear.org/album/1555418-puritan-bone-ecstasy-on-the-frontier-of-blood.php"
    },
    {
        "artist": "Paledusk",
        "album": "PALEDUSK",
        "release_date": "2025-11-26",
        "genre": "Metalcore",
        "url": "https://www.albumoftheyear.org/album/1494870-paledusk-paledusk.php"
    },
    {
        "artist": "Effluence",
        "album": "Effluence / Tantric Bile / Steve Matthews Trio",
        "release_date": "2025-11-24",
        "genre": "Death Metal",
        "url": "https://www.albumoftheyear.org/album/1551935-effluence-effluence-tantric-bile-steve-matthews-trio.php"
    },
    {
        "artist": "Grauwyler",
        "album": "Nullhymn",
        "release_date": "2025-11-23",
        "genre": "Black Metal",
        "url": "https://www.albumoftheyear.org/album/1556063-grauwyler-nullhymn.php"
    },
    {
        "artist": "Morbikon",
        "album": "Lost Within The Astral Crypts",
        "release_date": "2025-11-21",
        "genre": "Black Metal",
        "url": "https://www.albumoftheyear.org/album/1525365-morbikon-lost-within-the-astral-crypts.php"
    },
    {
        "artist": "The Halo Effect",
        "album": "We Are Shadows",
        "release_date": "2025-11-21",
        "genre": "Death Metal, Melodic Death Metal",
        "url": "https://www.albumoftheyear.org/album/1474708-the-halo-effect-we-are-shadows.php"
    },
    {
        "artist": "Depravity",
        "album": "Bestial Possession",
        "release_date": "2025-11-21",
        "genre": "Death Metal",
        "url": "https://www.albumoftheyear.org/album/1485029-depravity-bestial-possession.php"
    },
    {
        "artist": "When Nothing Remains",
        "album": "Echoes Of Eternal Night",
        "release_date": "2025-11-21",
        "genre": "Doom Metal",
        "url": "https://www.albumoftheyear.org/album/1525362-when-nothing-remains-echoes-of-eternal-night.php"
    },
    {
        "artist": "Annisokay",
        "album": "Abyss - The Final Chapter",
        "release_date": "2025-11-21",
        "genre": "Metalcore",
        "url": "https://www.albumoftheyear.org/album/1497346-annisokay-abyss-the-final-chapter.php"
    },
    {
        "artist": "Gasket",
        "album": "GASKET",
        "release_date": "2025-11-21",
        "genre": "Metalcore",
        "url": "https://www.albumoftheyear.org/album/1548969-gasket-gasket.php"
    },
    {
        "artist": "My Ticket Home",
        "album": "Pure To A Fault",
        "release_date": "2025-11-21",
        "genre": "Metalcore",
        "url": "https://www.albumoftheyear.org/album/1545928-my-ticket-home-pure-to-a-fault.php"
    },
    {
        "artist": "Amor De Dios",
        "album": "Heaven Sent",
        "release_date": "2025-11-21",
        "genre": "Metalcore",
        "url": "https://www.albumoftheyear.org/album/1549097-amor-de-dios-heaven-sent.php"
    },
    {
        "artist": "Graypath",
        "album": "The Vanishing Sequence",
        "release_date": "2025-11-21",
        "genre": "Metalcore",
        "url": "https://www.albumoftheyear.org/album/1549085-graypath-the-vanishing-sequence.php"
    },
    {
        "artist": "ExitWounds",
        "album": "An Offering to Tragedy",
        "release_date": "2025-11-21",
        "genre": "Metalcore",
        "url": "https://www.albumoftheyear.org/album/1485910-exitwounds-an-offering-to-tragedy.php"
    },
    {
        "artist": "Hetta",
        "album": "Acetate",
        "release_date": "2025-11-21",
        "genre": "Metalcore",
        "url": "https://www.albumoftheyear.org/album/1494186-hetta-acetate.php"
    },
    {
        "artist": "Bloodbound",
        "album": "Field Of Swords",
        "release_date": "2025-11-21",
        "genre": "Power Metal",
        "url": "https://www.albumoftheyear.org/album/1546137-bloodbound-field-of-swords.php"
    },
    {
        "artist": "Darktribe",
        "album": "Forgotten Reveries",
        "release_date": "2025-11-21",
        "genre": "Power Metal",
        "url": "https://www.albumoftheyear.org/album/1548629-darktribe-forgotten-reveries.php"
    },
    {
        "artist": "Born From Pain",
        "album": "SIEGE MENTALITY",
        "release_date": "2025-11-20",
        "genre": "Metalcore, Thrash Metal",
        "url": "https://www.albumoftheyear.org/album/1550817-born-from-pain-siege-mentality.php"
    },
    {
        "artist": "Angelmaker",
        "album": "This Used To Be Heaven",
        "release_date": "2025-11-20",
        "genre": "Metalcore",
        "url": "https://www.albumoftheyear.org/album/1504603-angelmaker-this-used-to-be-heaven.php"
    },
    {
        "artist": "Frontières",
        "album": "Rémanence",
        "release_date": "2025-11-19",
        "genre": "Metalcore",
        "url": "https://www.albumoftheyear.org/album/1549080-frontieres-remanence.php"
    },
    {
        "artist": "Zero Tolerance",
        "album": "A Test of Strength",
        "release_date": "2025-11-18",
        "genre": "Thrash Metal",
        "url": "https://www.albumoftheyear.org/album/1545743-zero-tolerance-a-test-of-strength.php"
    },
    {
        "artist": "Night Vigil",
        "album": "Night Vigil",
        "release_date": "2025-11-17",
        "genre": "Black Metal",
        "url": "https://www.albumoftheyear.org/album/1563174-night-vigil-night-vigil.php"
    },
    {
        "artist": "Netherwalker",
        "album": "Odyssey of Respair",
        "release_date": "2025-11-17",
        "genre": "Metalcore, Symphonic Metal",
        "url": "https://www.albumoftheyear.org/album/1488919-netherwalker-odyssey-of-respair.php"
    },
    {
        "artist": "구룡",
        "album": "노래하자! 전진하자!",
        "release_date": "2025-11-16",
        "genre": "Black Metal",
        "url": "https://www.albumoftheyear.org/album/1542427---.php"
    },
    {
        "artist": "Oathless One",
        "album": "Petrification Hex",
        "release_date": "2025-11-15",
        "genre": "Black Metal",
        "url": "https://www.albumoftheyear.org/album/1545643-oathless-one-petrification-hex.php"
    },
    {
        "artist": "Spared An Endless Orbit",
        "album": "Spared an Endless Orbit",
        "release_date": "2025-11-15",
        "genre": "Metalcore",
        "url": "https://www.albumoftheyear.org/album/1542152-spared-an-endless-orbit-spared-an-endless-orbit.php"
    },
    {
        "artist": "1914",
        "album": "Viribus Unitis",
        "release_date": "2025-11-14",
        "genre": "Black Metal, Blackened Death Metal, Death Metal",
        "url": "https://www.albumoftheyear.org/album/1438289-1914-viribus-unitis.php"
    },
    {
        "artist": "Veilburner",
        "album": "Longing for Triumph, Reeking of Tragedy",
        "release_date": "2025-11-14",
        "genre": "Black Metal",
        "url": "https://www.albumoftheyear.org/album/1454753-veilburner-longing-for-triumph-reeking-of-tragedy.php"
    },
    {
        "artist": "Lamp of Murmuur",
        "album": "The Dreaming Prince in Ecstasy",
        "release_date": "2025-11-14",
        "genre": "Black Metal",
        "url": "https://www.albumoftheyear.org/album/1470291-lamp-of-murmuur-the-dreaming-prince-in-ecstasy.php"
    },
    {
        "artist": "Strigiform",
        "album": "Aconite",
        "release_date": "2025-11-14",
        "genre": "Blackened Death Metal, Death Metal",
        "url": "https://www.albumoftheyear.org/album/1507193-strigiform-aconite.php"
    },
    {
        "artist": "Demon King",
        "album": "Death Knell",
        "release_date": "2025-11-14",
        "genre": "Blackened Death Metal, Death Metal",
        "url": "https://www.albumoftheyear.org/album/1386940-demon-king-death-knell.php"
    },
    {
        "artist": "VoidCeremony",
        "album": "Abditum",
        "release_date": "2025-11-14",
        "genre": "Death Metal",
        "url": "https://www.albumoftheyear.org/album/1481305-voidceremony-abditum.php"
    },
    {
        "artist": "Depleted",
        "album": "Remains",
        "release_date": "2025-11-14",
        "genre": "Doom Metal",
        "url": "https://www.albumoftheyear.org/album/1544227-depleted-remains.php"
    },
    {
        "artist": "Bell Witch",
        "album": "Stygian Bough, Vol. II",
        "release_date": "2025-11-14",
        "genre": "Doom Metal",
        "url": "https://www.albumoftheyear.org/album/1480031-bell-witch-stygian-bough-vol-ii.php"
    },
    {
        "artist": "Dark Entity",
        "album": "Dehumanize",
        "release_date": "2025-11-14",
        "genre": "Groove Metal, Metalcore",
        "url": "https://www.albumoftheyear.org/album/1540808-dark-entity-dehumanize.php"
    },
    {
        "artist": "False Reality",
        "album": "FADED INTENTIONS",
        "release_date": "2025-11-14",
        "genre": "Metalcore, Thrash Metal",
        "url": "https://www.albumoftheyear.org/album/1505274-false-reality-faded-intentions.php"
    },
    {
        "artist": "Of Mice & Men",
        "album": "Another Miracle",
        "release_date": "2025-11-14",
        "genre": "Metalcore",
        "url": "https://www.albumoftheyear.org/album/1386115-of-mice-men-another-miracle.php"
    },
    {
        "artist": "fr3ak",
        "album": "thelasttimeyousawme",
        "release_date": "2025-11-14",
        "genre": "Metalcore",
        "url": "https://www.albumoftheyear.org/album/1567152-fr3ak-thelasttimeyousawme.php"
    },
    {
        "artist": "So Far So Good",
        "album": "So Far So Good",
        "release_date": "2025-11-14",
        "genre": "Metalcore",
        "url": "https://www.albumoftheyear.org/album/1540356-so-far-so-good-so-far-so-good.php"
    },
    {
        "artist": "Osiah",
        "album": "Aion",
        "release_date": "2025-11-14",
        "genre": "Metalcore",
        "url": "https://www.albumoftheyear.org/album/1521021-osiah-aion.php"
    },
    {
        "artist": "Stellar Circuits",
        "album": "Phantom : : Phoenix",
        "release_date": "2025-11-14",
        "genre": "Progressive Metal",
        "url": "https://www.albumoftheyear.org/album/1456805-stellar-circuits-phantom-phoenix.php"
    },
    {
        "artist": "Various Artists",
        "album": "No Life ‘Til Leather - A Tribute To Metallica’s Kill ‘Em All",
        "release_date": "2025-11-14",
        "genre": "Thrash Metal",
        "url": "https://www.albumoftheyear.org/album/1541542-various-artists-no-life-til-leather-a-tribute-to-metallicas-kill-em-all.php"
    },
    {
        "artist": "The Reticent",
        "album": "Please",
        "release_date": "2025-11-13",
        "genre": "Progressive Metal",
        "url": "https://www.albumoftheyear.org/album/1470421-the-reticent-please.php"
    },
    {
        "artist": "Lethaea",
        "album": "Demo I",
        "release_date": "2025-11-12",
        "genre": "Black Metal",
        "url": "https://www.albumoftheyear.org/album/1543468-lethaea-demo-i.php"
    },
    {
        "artist": "CURSES",
        "album": "BORN FROM PAIN",
        "release_date": "2025-11-11",
        "genre": "Metalcore",
        "url": "https://www.albumoftheyear.org/album/1535667-curses-born-from-pain.php"
    },
    {
        "artist": "Moonflower",
        "album": "The Infinite Garden",
        "release_date": "2025-11-09",
        "genre": "Metalcore, Progressive Metal",
        "url": "https://www.albumoftheyear.org/album/1535011-moonflower-the-infinite-garden.php"
    },
    {
        "artist": "Kostnatění",
        "album": "Přílišnost (Excess)",
        "release_date": "2025-11-07",
        "genre": "Black Metal",
        "url": "https://www.albumoftheyear.org/album/1455849-kostnateni-prilisnost-excess.php"
    },
    {
        "artist": "Tatterdemalion",
        "album": "Ultraterrestrial",
        "release_date": "2025-11-07",
        "genre": "Black Metal",
        "url": "https://www.albumoftheyear.org/album/1545326-tatterdemalion-ultraterrestrial.php"
    },
    {
        "artist": "Qrixkuor",
        "album": "The Womb of the World",
        "release_date": "2025-11-07",
        "genre": "Blackened Death Metal, Death Metal",
        "url": "https://www.albumoftheyear.org/album/1456182-qrixkuor-the-womb-of-the-world.php"
    },
    {
        "artist": "Omnium Gatherum",
        "album": "May The Bridges We Burn Light The Way",
        "release_date": "2025-11-07",
        "genre": "Death Metal, Melodic Death Metal",
        "url": "https://www.albumoftheyear.org/album/1423217-omnium-gatherum-may-the-bridges-we-burn-light-the-way.php"
    },
    {
        "artist": "Glorious Depravity",
        "album": "Death Never Sleeps",
        "release_date": "2025-11-07",
        "genre": "Death Metal",
        "url": "https://www.albumoftheyear.org/album/1461350-glorious-depravity-death-never-sleeps.php"
    },
    {
        "artist": "Ophidian Memory",
        "album": "Seraphim",
        "release_date": "2025-11-07",
        "genre": "Death Metal, Melodic Death Metal",
        "url": "https://www.albumoftheyear.org/album/1530415-ophidian-memory-seraphim.php"
    },
    {
        "artist": "Oromet",
        "album": "The Sinking Isle",
        "release_date": "2025-11-07",
        "genre": "Doom Metal",
        "url": "https://www.albumoftheyear.org/album/1509148-oromet-the-sinking-isle.php"
    },
    {
        "artist": "Moonstone",
        "album": "Age of Mycology",
        "release_date": "2025-11-07",
        "genre": "Doom Metal",
        "url": "https://www.albumoftheyear.org/album/1532728-moonstone-age-of-mycology.php"
    },
    {
        "artist": "Novembre",
        "album": "Words of Indigo",
        "release_date": "2025-11-07",
        "genre": "Gothic Metal, Progressive Metal",
        "url": "https://www.albumoftheyear.org/album/1470465-novembre-words-of-indigo.php"
    },
    {
        "artist": "Pupil Slicer",
        "album": "Fleshwork",
        "release_date": "2025-11-07",
        "genre": "Metalcore",
        "url": "https://www.albumoftheyear.org/album/1442083-pupil-slicer-fleshwork.php"
    },
    {
        "artist": "Cold Steel",
        "album": "Discipline & Punish",
        "release_date": "2025-11-07",
        "genre": "Metalcore, Thrash Metal",
        "url": "https://www.albumoftheyear.org/album/1453579-cold-steel-discipline-punish.php"
    },
    {
        "artist": "Drain",
        "album": "…IS YOUR FRIEND",
        "release_date": "2025-11-07",
        "genre": "Metalcore, Thrash Metal",
        "url": "https://www.albumoftheyear.org/album/1347004-drain-is-your-friend.php"
    },
    {
        "artist": "Northlane",
        "album": "Node: Reloaded",
        "release_date": "2025-11-07",
        "genre": "Metalcore, Progressive Metal",
        "url": "https://www.albumoftheyear.org/album/1496285-northlane-node-reloaded.php"
    },
    {
        "artist": "Emancipation",
        "album": "When The Heavens Opened... Bodies Fell",
        "release_date": "2025-11-07",
        "genre": "Metalcore",
        "url": "https://www.albumoftheyear.org/album/1567021-emancipation-when-the-heavens-opened-bodies-fell.php"
    },
    {
        "artist": "Bore",
        "album": "Feral",
        "release_date": "2025-11-07",
        "genre": "Metalcore",
        "url": "https://www.albumoftheyear.org/album/1531055-bore-feral.php"
    },
    {
        "artist": "Astronoid",
        "album": "Stargod",
        "release_date": "2025-11-07",
        "genre": "Progressive Metal",
        "url": "https://www.albumoftheyear.org/album/1499268-astronoid-stargod.php"
    },
    {
        "artist": "NekroKratie",
        "album": "Geschichten Aus Dem Schornstein",
        "release_date": "2025-11-06",
        "genre": "Black Metal",
        "url": "https://www.albumoftheyear.org/album/1530047-nekrokratie-geschichten-aus-dem-schornstein.php"
    },
    {
        "artist": "Hive",
        "album": "Conduct of Flies",
        "release_date": "2025-11-05",
        "genre": "Metalcore",
        "url": "https://www.albumoftheyear.org/album/1518701-hive-conduct-of-flies.php"
    },
    {
        "artist": "onegirl37razors",
        "album": "Demo",
        "release_date": "2025-11-04",
        "genre": "Metalcore",
        "url": "https://www.albumoftheyear.org/album/1530015-onegirl37razors-demo.php"
    },
    {
        "artist": "Shivered",
        "album": "Chains",
        "release_date": "2025-11-02",
        "genre": "Doom Metal",
        "url": "https://www.albumoftheyear.org/album/1522728-shivered-chains.php"
    },
    {
        "artist": "Stworz",
        "album": "U śmierci na komornem",
        "release_date": "2025-11-01",
        "genre": "Black Metal",
        "url": "https://www.albumoftheyear.org/album/1523365-stworz-u-smierci-na-komornem.php"
    },
    {
        "artist": "xfortunex",
        "album": "The Blueprint",
        "release_date": "2025-11-01",
        "genre": "Metalcore",
        "url": "https://www.albumoftheyear.org/album/1528722-xfortunex-the-blueprint.php"
    },
    {
        "artist": "Nonel",
        "album": "Eclipse",
        "release_date": "2025-11-01",
        "genre": "Metalcore, Progressive Metal",
        "url": "https://www.albumoftheyear.org/album/1524204-nonel-eclipse.php"
    },
    {
        "artist": "Pedestal For Leviathan",
        "album": "Enter: Vampyric Manifestation",
        "release_date": "2025-10-31",
        "genre": "Black Metal, Death Metal",
        "url": "https://www.albumoftheyear.org/album/1527128-pedestal-for-leviathan-enter-vampyric-manifestation.php"
    },
    {
        "artist": "THRON",
        "album": "Vurias",
        "release_date": "2025-10-31",
        "genre": "Black Metal",
        "url": "https://www.albumoftheyear.org/album/1448432-thron-vurias.php"
    },
    {
        "artist": "Heraldic Blaze",
        "album": "Monument of Will",
        "release_date": "2025-10-31",
        "genre": "Black Metal",
        "url": "https://www.albumoftheyear.org/album/1525891-heraldic-blaze-monument-of-will.php"
    },
    {
        "artist": "One Of Nine",
        "album": "Dawn of the Iron Shadow",
        "release_date": "2025-10-31",
        "genre": "Black Metal",
        "url": "https://www.albumoftheyear.org/album/1416008-one-of-nine-dawn-of-the-iron-shadow.php"
    },
    {
        "artist": "Malakhim",
        "album": "And In Our Hearts The Devil Sings",
        "release_date": "2025-10-31",
        "genre": "Black Metal",
        "url": "https://www.albumoftheyear.org/album/1440059-malakhim-and-in-our-hearts-the-devil-sings.php"
    },
    {
        "artist": "Yellow Eyes",
        "album": "Confusion Gate",
        "release_date": "2025-10-31",
        "genre": "Black Metal",
        "url": "https://www.albumoftheyear.org/album/1521310-yellow-eyes-confusion-gate.php"
    },
    {
        "artist": "Trivium",
        "album": "Struck Dead",
        "release_date": "2025-10-31",
        "genre": "Death Metal, Melodic Death Metal, Metalcore, Thrash Metal",
        "url": "https://www.albumoftheyear.org/album/1421440-trivium-struck-dead.php"
    },
    {
        "artist": "Avatar",
        "album": "Don’t Go In The Forest",
        "release_date": "2025-10-31",
        "genre": "Death Metal, Melodic Death Metal",
        "url": "https://www.albumoftheyear.org/album/1445702-avatar-dont-go-in-the-forest.php"
    },
    {
        "artist": "Aephanemer",
        "album": "Utopie",
        "release_date": "2025-10-31",
        "genre": "Death Metal, Melodic Death Metal, Symphonic Metal",
        "url": "https://www.albumoftheyear.org/album/1445432-aephanemer-utopie.php"
    },
    {
        "artist": "Stillbirth",
        "album": "Survival Protocol",
        "release_date": "2025-10-31",
        "genre": "Death Metal",
        "url": "https://www.albumoftheyear.org/album/1489963-stillbirth-survival-protocol.php"
    },
    {
        "artist": "BLOXECTOMY",
        "album": "BLOXECTOMY",
        "release_date": "2025-10-31",
        "genre": "Death Metal",
        "url": "https://www.albumoftheyear.org/album/1493924-bloxectomy-bloxectomy.php"
    },
    {
        "artist": "Primitive Man",
        "album": "Observance",
        "release_date": "2025-10-31",
        "genre": "Doom Metal",
        "url": "https://www.albumoftheyear.org/album/1454587-primitive-man-observance.php"
    },
    {
        "artist": "Aviana",
        "album": "Void",
        "release_date": "2025-10-31",
        "genre": "Metalcore",
        "url": "https://www.albumoftheyear.org/album/1479354-aviana-void.php"
    },
    {
        "artist": "Bloom",
        "album": "The Light We Chase",
        "release_date": "2025-10-31",
        "genre": "Metalcore",
        "url": "https://www.albumoftheyear.org/album/1429340-bloom-the-light-we-chase.php"
    },
    {
        "artist": "Despised Icon",
        "album": "Shadow Work",
        "release_date": "2025-10-31",
        "genre": "Metalcore",
        "url": "https://www.albumoftheyear.org/album/1405790-despised-icon-shadow-work.php"
    },
    {
        "artist": "DEEZ NUTS",
        "album": "Saudade",
        "release_date": "2025-10-31",
        "genre": "Metalcore",
        "url": "https://www.albumoftheyear.org/album/1520969-deez-nuts-saudade.php"
    },
    {
        "artist": "Howling Giant",
        "album": "Crucible & Ruin",
        "release_date": "2025-10-31",
        "genre": "Progressive Metal",
        "url": "https://www.albumoftheyear.org/album/1476165-howling-giant-crucible-ruin.php"
    },
    {
        "artist": "Unprocessed",
        "album": "Angel",
        "release_date": "2025-10-31",
        "genre": "Progressive Metal",
        "url": "https://www.albumoftheyear.org/album/1426953-unprocessed-angel.php"
    },
    {
        "artist": "Currents",
        "album": "All That Follows",
        "release_date": "2025-10-31",
        "genre": "Progressive Metal",
        "url": "https://www.albumoftheyear.org/album/1520237-currents-all-that-follows.php"
    },
    {
        "artist": "Black Soul Horde",
        "album": "Symphony of Chaos",
        "release_date": "2025-10-31",
        "genre": "Power Metal",
        "url": "https://www.albumoftheyear.org/album/1521264-black-soul-horde-symphony-of-chaos.php"
    },
    {
        "artist": "Cemican",
        "album": "Uk'u'uk' Ankil Mayakaaj",
        "release_date": "2025-10-31",
        "genre": "Power Metal",
        "url": "https://www.albumoftheyear.org/album/1489968-cemican-ukuuk-ankil-mayakaaj.php"
    },
    {
        "artist": "Bastard Cröss",
        "album": "Crossripper",
        "release_date": "2025-10-31",
        "genre": "Thrash Metal",
        "url": "https://www.albumoftheyear.org/album/1444754-bastard-cross-crossripper.php"
    },
    {
        "artist": "Misanthropic Might",
        "album": "Qualzucht",
        "release_date": "2025-10-30",
        "genre": "Blackened Death Metal, Death Metal",
        "url": "https://www.albumoftheyear.org/album/1536956-misanthropic-might-qualzucht.php"
    },
    {
        "artist": "Psithurism",
        "album": "Origins",
        "release_date": "2025-10-30",
        "genre": "Progressive Metal",
        "url": "https://www.albumoftheyear.org/album/1520417-psithurism-origins.php"
    },
    {
        "artist": "Deadbolt Hc",
        "album": "DISILLUSION",
        "release_date": "2025-10-27",
        "genre": "Thrash Metal",
        "url": "https://www.albumoftheyear.org/album/1525241-deadbolt-hc-disillusion.php"
    }
]